setup.py
cv_monitor/__init__.py
cv_monitor.egg-info/PKG-INFO
cv_monitor.egg-info/SOURCES.txt
cv_monitor.egg-info/dependency_links.txt
cv_monitor.egg-info/requires.txt
cv_monitor.egg-info/top_level.txt
cv_monitor/otcbtc_eos/__init__.py
cv_monitor/otcbtc_eos/conf.py
cv_monitor/otcbtc_eos/index.py