Metadata-Version: 1.0
Name: cv-monitor
Version: 1.0.2
Summary: Monitor virtual currency through exchanges
Home-page: https://github.com/lovefive5/cv_monitor
Author: lovefive5
Author-email: 2845652616@qq.com
License: MIT License
Keywords: eos,btc,eth
Platform: any
